README.md
setup.cfg
setup.py
Gloat_Matcher.egg-info/PKG-INFO
Gloat_Matcher.egg-info/SOURCES.txt
Gloat_Matcher.egg-info/dependency_links.txt
Gloat_Matcher.egg-info/entry_points.txt
Gloat_Matcher.egg-info/requires.txt
Gloat_Matcher.egg-info/top_level.txt
gloat_matcher.egg-info/PKG-INFO
gloat_matcher.egg-info/SOURCES.txt
gloat_matcher.egg-info/dependency_links.txt
gloat_matcher.egg-info/entry_points.txt
gloat_matcher.egg-info/requires.txt
gloat_matcher.egg-info/top_level.txt
src/Candidate.py
src/CandidateFinder.py
src/Job.py
src/Runner.py
src/Skills.py
src/__init__.py
src/resources/__init__.py
src/resources/database.json
src/tests/__init__.py
src/tests/matcher_tests.py