Metadata-Version: 1.2
Name: gloat-matcher
Version: 0.2
Summary: Backend assigment for Gloat
Home-page: UNKNOWN
License: UNKNOWN
Download-URL: https://github.com/Rantzur1992/gloat-backend/archive/0.1.tar.gz
Platform: UNKNOWN
Requires-Python: >3.7
